{
    "2026-06-21": {
        "love0.rf.gd": {
            "visits": 1
        },
        "pvtchat11.localhost": {
            "visits": 1
        }
    },
    "2026-06-05": {
        "love0.rf.gd": {
            "visits": 2
        }
    },
    "2026-06-03": {
        "love0.rf.gd": {
            "visits": 1
        }
    },
    "2026-05-31": {
        "love0.rf.gd": {
            "visits": 1
        },
        "pvtchat11.localhost": {
            "visits": 1
        }
    },
    "2026-05-26": {
        "love0.rf.gd": {
            "visits": 1
        }
    },
    "2026-05-24": {
        "love0.rf.gd": {
            "visits": 1
        }
    },
    "2026-05-17": {
        "love0.rf.gd": {
            "visits": 1
        }
    },
    "2026-05-16": {
        "love0.rf.gd": {
            "visits": 1
        }
    },
    "2026-05-13": {
        "love0.rf.gd": {
            "visits": 1
        }
    },
    "2026-05-03": {
        "love0.rf.gd": {
            "visits": 1
        }
    },
    "2026-04-30": {
        "love0.rf.gd": {
            "visits": 1
        },
        "pvtchat10.localhost": {
            "visits": 1
        }
    },
    "2026-04-28": {
        "love0.rf.gd": {
            "visits": 1
        }
    },
    "2026-04-25": {
        "love0.rf.gd": {
            "visits": 1
        }
    },
    "2026-04-23": {
        "love0.rf.gd": {
            "visits": 1
        }
    },
    "2026-04-20": {
        "love0.rf.gd": {
            "visits": 1
        }
    },
    "2026-04-18": {
        "love0.rf.gd": {
            "visits": 1
        }
    },
    "2026-04-17": {
        "love0.rf.gd": {
            "visits": 2
        },
        "pvtchat11.localhost": {
            "visits": 1
        }
    },
    "2026-04-16": {
        "x0.rf.gd": {
            "visits": 1
        }
    },
    "2026-04-15": {
        "love0.rf.gd": {
            "visits": 2
        }
    },
    "2026-04-14": {
        "love0.rf.gd": {
            "visits": 2
        },
        "pvtchat11.localhost": {
            "visits": 3
        },
        "pvtchat10.localhost": {
            "visits": 3
        }
    },
    "2026-04-13": {
        "love0.rf.gd": {
            "visits": 32
        },
        "pvtchat11.localhost": {
            "visits": 2
        },
        "pvtchat10.localhost": {
            "visits": 1
        }
    }
}